serger/__init__.py
serger/__main__.py
serger/actions.py
serger/build.py
serger/cli.py
serger/config/__init__.py
serger/config/config_loader.py
serger/config/config_resolve.py
serger/config/config_types.py
serger/config/config_validate.py
serger/constants.py
serger/logs.py
serger/main_config.py
serger/meta.py
serger/module_actions.py
serger/py.typed
serger/selftest.py
serger/stitch.py
serger/utils/__init__.py
serger/utils/utils_installed_packages.py
serger/utils/utils_matching.py
serger/utils/utils_modules.py
serger/utils/utils_paths.py
serger/utils/utils_types.py
serger/utils/utils_validation.py
serger/verify_script.py
serger-0.2.0.dist-info/METADATA
serger-0.2.0.dist-info/WHEEL
serger-0.2.0.dist-info/entry_points.txt
serger-0.2.0.dist-info/licenses/LICENSE
serger-0.2.0.dist-info/RECORD
