Metadata-Version: 2.4
Name: serger
Version: 0.2.0
Summary: Stitch your module into a single file
License-File: LICENSE
Keywords: module,packaging,single-file
Author: Apathetic Tools
Requires-Python: >=3.10
Classifier: Development Status :: 3 - Alpha
Classifier: Environment :: Console
Classifier: Intended Audience :: Developers
Classifier: Operating System :: OS Independent
Classifier: Programming Language :: Python :: 3
Classifier: Programming Language :: Python :: 3 :: Only
Classifier: Programming Language :: Python :: 3.10
Classifier: Programming Language :: Python :: 3.11
Classifier: Programming Language :: Python :: 3.12
Classifier: Topic :: Software Development :: Build Tools
Requires-Dist: apathetic-logging (>=0.0.1,<2.0.0)
Requires-Dist: apathetic-schema (>=0.0.1,<2.0.0)
Requires-Dist: apathetic-utils (>=0.0.1,<2.0.0)
Project-URL: Changelog, https://github.com/apathetic-tools/serger/releases
Project-URL: Documentation, https://apathetic-tools.github.io/serger/
Project-URL: Homepage, https://github.com/apathetic-tools/serger
Project-URL: Issues, https://github.com/apathetic-tools/serger/issues
Project-URL: Repository, https://github.com/apathetic-tools/serger
